capsem_proxy/__init__.py
capsem_proxy/capsem_integration.py
capsem_proxy/models.py
capsem_proxy/server.py
capsem_proxy/api/__init__.py
capsem_proxy/api/gemini.py
capsem_proxy/api/openai.py
capsem_proxy/providers/__init__.py
capsem_proxy/providers/gemini.py
capsem_proxy/providers/openai.py
capsem_proxy/security/__init__.py
capsem_proxy/security/identity.py
capsem_proxy-0.1.0.dist-info/METADATA
capsem_proxy-0.1.0.dist-info/WHEEL
capsem_proxy-0.1.0.dist-info/RECORD
