Metadata-Version: 2.4
Name: capsem-proxy
Version: 0.1.0
Summary: Multi-tenant LLM proxy with CAPSEM security policy enforcement
Requires-Python: >=3.11
Requires-Dist: capsem>=0.2.0
Requires-Dist: fastapi>=0.118.2
Requires-Dist: google-genai>=1.42.0
Requires-Dist: httptools>=0.7.1
Requires-Dist: httpx>=0.28.1
Requires-Dist: openai>=1.59.0
Requires-Dist: python-dotenv>=1.1.1
Requires-Dist: uvicorn>=0.37.0
Requires-Dist: uvtools>=0.2.0
